aiobestproxiesapi/__init__.py
aiobestproxiesapi/api.py
aiobestproxiesapi/exceptions.py
aiobestproxiesapi/helpers.py
aiobestproxiesapi/params.py
aiobestproxiesapi/types.py
aiobestproxiesapi-0.0.2.dist-info/LICENSE
aiobestproxiesapi-0.0.2.dist-info/METADATA
aiobestproxiesapi-0.0.2.dist-info/WHEEL
aiobestproxiesapi-0.0.2.dist-info/top_level.txt
aiobestproxiesapi-0.0.2.dist-info/RECORD
